{"v":"4.8.0","meta":{"g":"LottieFiles AE 3.0.2","a":"","k":"","d":"","tc":""},"fr":60,"ip":0,"op":300,"w":500,"h":500,"nm":"Email Icon","ddd":0,"assets":[],"layers":[{"ddd":0,"ind":1,"ty":4,"nm":"Email icon 2","sr":1,"ks":{"o":{"a":0,"k":100,"ix":11},"r":{"a":0,"k":0,"ix":10},"p":{"a":0,"k":[250,240,0],"ix":2},"a":{"a":0,"k":[0,0,0],"ix":1},"s":{"a":0,"k":[100,100,100],"ix":6}},"ao":0,"shapes":[{"ty":"gr","it":[{"ind":0,"ty":"sh","ix":1,"ks":{"a":0,"k":{"i":[[0,0],[-77.09,-1.124],[-15.745,-0.232],[-13.644,-3.28],[-1.687,-20.499],[-0.582,-42.506],[-0.891,-18.62],[-0.344,-10.27],[13.49,-7.538],[7.788,-0.526],[17.093,-0.485],[61.45,0.899],[29.435,4.995],[2.357,20.015],[-0.517,32.271],[-1.175,31.881],[-17.335,4.325],[-17.137,-11.809],[-37.551,-26.915],[-1.685,-0.311],[-2.67,2.455],[-25.44,18.904],[-13.459,8.323],[-9.92,-7.385],[1.659,-4.639],[5.229,-5.388],[21.346,-16.244],[25.544,-18.059],[5.801,0.084],[7.36,5.715],[8.282,6.124],[27.367,20.313],[-14.31,10.744],[-0.343,0.194],[-2.083,-0.384],[-7.395,-9.087]],"o":[[77.1,0.256],[15.745,0.23],[13.843,0.204],[21.991,5.286],[3.49,42.413],[0.255,18.641],[0.49,10.226],[0.477,14.245],[-6.814,3.808],[-17.06,1.153],[-61.43,1.742],[-29.871,-0.437],[-22.149,-3.759],[-3.782,-32.119],[0.511,-31.89],[0.48,-13.017],[23.013,-5.74],[38.043,26.215],[1.393,0.998],[3.567,0.658],[23.321,-21.44],[12.7,-9.437],[8.063,-4.986],[3.952,2.942],[-2.528,7.07],[-18.724,19.294],[-24.903,18.952],[-4.735,3.347],[-9.715,-0.14],[-8.13,-6.312],[-27.406,-20.265],[-6.591,-4.892],[0.32,-0.23],[1.851,-1.028],[11.632,2.146],[0,0]],"v":[[-158.818,-154.79],[72.471,-152.024],[119.705,-151.335],[161.917,-149.844],[193.015,-105.887],[195.907,21.595],[197.841,77.485],[199.915,108.2],[184.161,145.453],[161.65,151.158],[110.325,152.927],[-74.035,154.377],[-164.381,149.99],[-196.847,105.883],[-199.611,9.213],[-197.5,-86.396],[-182.186,-134.84],[-113.432,-101.146],[-0.878,-20.31],[3.654,-17.976],[13.135,-22.425],[85.891,-83.538],[125.103,-110.267],[165.192,-125.501],[167.406,-111.901],[154.543,-93.628],[92.785,-41.913],[16.737,13.054],[1.034,19.806],[-24.746,7.713],[-49.29,-11.029],[-132.621,-70.186],[-162.1,-111.648],[-161.106,-112.285],[-154.899,-112.726],[-125.42,-94.298]],"c":false},"ix":2},"nm":"Path 1","mn":"ADBE Vector Shape - Group","hd":false},{"ty":"st","c":{"a":0,"k":[0,0,0,1],"ix":3},"o":{"a":0,"k":100,"ix":4},"w":{"a":0,"k":7,"ix":5},"lc":2,"lj":2,"bm":0,"nm":"Stroke 1","mn":"ADBE Vector Graphic - Stroke","hd":false},{"ty":"tr","p":{"a":0,"k":[0,0],"ix":2},"a":{"a":0,"k":[0,0],"ix":1},"s":{"a":0,"k":[100,100],"ix":3},"r":{"a":0,"k":0,"ix":6},"o":{"a":0,"k":100,"ix":7},"sk":{"a":0,"k":0,"ix":4},"sa":{"a":0,"k":0,"ix":5},"nm":"Transform"}],"nm":"Group 1","np":2,"cix":2,"bm":0,"ix":1,"mn":"ADBE Vector Group","hd":false},{"ty":"tm","s":{"a":0,"k":0,"ix":1},"e":{"a":1,"k":[{"i":{"x":[0.667],"y":[1]},"o":{"x":[0.333],"y":[0]},"t":0,"s":[0]},{"t":240,"s":[100]}],"ix":2},"o":{"a":0,"k":0,"ix":3},"m":1,"ix":2,"nm":"Trim Paths 1","mn":"ADBE Vector Filter - Trim","hd":false}],"ip":0,"op":300,"st":0,"bm":0},{"ddd":0,"ind":2,"ty":4,"nm":"Email icon","sr":1,"ks":{"o":{"a":1,"k":[{"i":{"x":[0.833],"y":[0.833]},"o":{"x":[0.167],"y":[0.167]},"t":0,"s":[0]},{"t":240,"s":[100]}],"ix":11},"r":{"a":0,"k":0,"ix":10},"p":{"a":0,"k":[250,250,0],"ix":2},"a":{"a":0,"k":[0,0,0],"ix":1},"s":{"a":0,"k":[100,100,100],"ix":6}},"ao":0,"shapes":[{"ty":"gr","it":[{"ind":0,"ty":"sh","ix":1,"ks":{"a":0,"k":{"i":[[21.62,0],[0,0],[17.405,20.779],[0,0],[-21.62,0],[0,0],[0,0],[0,-21.62],[0,0]],"o":[[0,0],[-14.913,-0.324],[0,0],[0,-21.62],[0,0],[0,0],[21.62,0],[0,0],[0,21.62]],"v":[[157.853,145.5],[-163.853,145.5],[-197,112.5],[-194,-111.5],[-163.853,-145.5],[7,-27.5],[151,-139.5],[197,-106.353],[197,106.353]],"c":true},"ix":2},"nm":"Path 1","mn":"ADBE Vector Shape - Group","hd":false},{"ty":"fl","c":{"a":0,"k":[1,0.262745112181,0.262745112181,1],"ix":4},"o":{"a":0,"k":100,"ix":5},"r":1,"bm":0,"nm":"Fill 1","mn":"ADBE Vector Graphic - Fill","hd":false},{"ty":"tr","p":{"a":0,"k":[0,0],"ix":2},"a":{"a":0,"k":[0,0],"ix":1},"s":{"a":0,"k":[100,100],"ix":3},"r":{"a":0,"k":0,"ix":6},"o":{"a":0,"k":100,"ix":7},"sk":{"a":0,"k":0,"ix":4},"sa":{"a":0,"k":0,"ix":5},"nm":"Transform"}],"nm":"Group 1","np":2,"cix":2,"bm":0,"ix":1,"mn":"ADBE Vector Group","hd":false}],"ip":0,"op":300,"st":0,"bm":0}],"markers":[]}